xbus.broker-0.2.0-py3.4-nspkg.pth
xbus/broker/__init__.py
xbus/broker/cli/__init__.py
xbus/broker/cli/setup_application.py
xbus/broker/cli/start_server.py
xbus/broker/cli/main.py
xbus/broker/core/db.py
xbus/broker/core/__init__.py
xbus/broker/core/base.py
xbus/broker/core/features.py
xbus/broker/core/front/rpc.py
xbus/broker/core/front/__init__.py
xbus/broker/core/back/rpc.py
xbus/broker/core/back/envelope.py
xbus/broker/core/back/__init__.py
xbus/broker/core/back/node.py
xbus/broker/core/back/recipient.py
xbus/broker/core/back/event.py
xbus/broker/model/helpers.py
xbus/broker/model/service.py
xbus/broker/model/__init__.py
xbus/broker/model/logging.py
xbus/broker/model/input.py
xbus/broker/model/types.py
xbus/broker/model/emission.py
xbus/broker/model/event.py
xbus/broker/model/setupmodel.py
xbus/broker/model/auth/helpers.py
xbus/broker/model/auth/__init__.py
xbus/broker/model/auth/main.py
xbus.broker-0.2.0.dist-info/metadata.json
xbus.broker-0.2.0.dist-info/METADATA
xbus.broker-0.2.0.dist-info/entry_points.txt
xbus.broker-0.2.0.dist-info/WHEEL
xbus.broker-0.2.0.dist-info/namespace_packages.txt
xbus.broker-0.2.0.dist-info/top_level.txt
xbus.broker-0.2.0.dist-info/DESCRIPTION.rst
xbus.broker-0.2.0.dist-info/RECORD
