Metadata-Version: 2.0
Name: xbus.broker
Version: 0.2.0
Summary: Xbus Broker written in Python3
Home-page: https://bitbucket.org/xcg/xbus.broker
Author: Florent Aide
Author-email: florent.aide@xcg-consulting.fr
License: UNKNOWN
Keywords: xbus
Platform: UNKNOWN
Classifier: Development Status :: 4 - Beta
Classifier: Environment :: Console
Classifier: Intended Audience :: Developers
Classifier: Intended Audience :: Financial and Insurance Industry
Classifier: Intended Audience :: Information Technology
Classifier: Intended Audience :: Other Audience
Classifier: Intended Audience :: Science/Research
Classifier: Intended Audience :: System Administrators
Classifier: License :: OSI Approved :: MIT License
Classifier: Operating System :: OS Independent
Classifier: Programming Language :: Python :: 3.4
Classifier: Programming Language :: Python :: Implementation :: CPython
Requires-Dist: aiopg (==0.5.1)
Requires-Dist: aioredis
Requires-Dist: aiozmq
Requires-Dist: hiredis
Requires-Dist: msgpack-python (==0.4.3)
Requires-Dist: psycopg2 (==2.5.4)
Requires-Dist: pyzmq (==14.4.1)
Requires-Dist: SQLAlchemy (==0.9.8)
